command/__init__.py
command/command.py
command/utilities.py
command_known_as_dan-1.2.7.dist-info/LICENSE
command_known_as_dan-1.2.7.dist-info/METADATA
command_known_as_dan-1.2.7.dist-info/WHEEL
command_known_as_dan-1.2.7.dist-info/top_level.txt
command_known_as_dan-1.2.7.dist-info/RECORD
