Metadata-Version: 2.1
Name: command-known-as-dan
Version: 1.2.7
Summary: Command is a simple framework for handling command execution within your python application.
Home-page: https://github.com/known-as-dan/command-pypi
Author: known-as-dan
Author-email: dan@gotoindex.com
License: UNKNOWN
Platform: UNKNOWN
Classifier: Programming Language :: Python :: 3
Classifier: License :: OSI Approved :: MIT License
Classifier: Operating System :: OS Independent
Requires-Python: >=3.6
